README
setup.py
abpig/__init__.py
abpig/__main__.py
abpig/index.tmpl
abpig.egg-info/PKG-INFO
abpig.egg-info/SOURCES.txt
abpig.egg-info/dependency_links.txt
abpig.egg-info/requires.txt
abpig.egg-info/top_level.txt