Metadata-Version: 1.0
Name: abpig
Version: 0.4.3
Summary: A Better Python Image Gallery
Home-page: UNKNOWN
Author: Sean Olson
Author-email: seandolson654@gmail.com
License: MIT
Platform: UNKNOWN
